README.rst
setup.py
boto/__init__.py
boto/mturk/__init__.py
otree_boto2_shim.egg-info/PKG-INFO
otree_boto2_shim.egg-info/SOURCES.txt
otree_boto2_shim.egg-info/dependency_links.txt
otree_boto2_shim.egg-info/not-zip-safe
otree_boto2_shim.egg-info/top_level.txt