Metadata-Version: 1.0
Name: otree-boto2-shim
Version: 0.3.1
Summary: Shim package so that boto2 imports don't fail when using oTree.
Home-page: http://www.otree.org
Author: Chris
Author-email: chris@otree.org
License: MIT
Platform: UNKNOWN
